Robocon_24/Robocon_24.py
Robocon_24/__init__.py
Robocon_24/ball_detection.py
Robocon_24/camtest.py
Robocon_24/finding_shortest_ball.py
Robocon_24/image_to_rack.py
Robocon_24/logitech_test.py
Robocon_24/realsense_test.py
Robocon_24-1.0.1.dist-info/LICENSE
Robocon_24-1.0.1.dist-info/METADATA
Robocon_24-1.0.1.dist-info/WHEEL
Robocon_24-1.0.1.dist-info/top_level.txt
Robocon_24-1.0.1.dist-info/RECORD
