Metadata-Version: 2.1
Name: Robocon_24
Version: 1.0.1
Summary: This project is designed to detect balls and make decisions based on their positions in the context of a Robocon competition.
Home-page: https://github.com/mariswarycharan/Robocon_24_version
Author: Charan A A
Author-email: mariswarycharan@gmail.com
Project-URL: Homepage, https://github.com/mariswarycharan/Robocon_24_version
Project-URL: Download, https://github.com/mariswarycharan/Robocon_24_version.git
Project-URL: Documentation, https://github.com/mariswarycharan/Robocon_24_version/blob/main/README.md
Project-URL: Issue tracker, https://github.com/mariswarycharan/Robocon_24_version/issues
Project-URL: Source code, https://github.com/mariswarycharan/Robocon_24_version
Project-URL: GitHub Statistics, https://github.com/mariswarycharan/Robocon_24_version
Keywords: Robocon,Ball,Detection,Decision,Making,Computer Vision,YOLO,Ultralytics,OpenCV,Python,Ball Detection,Ball Decision Making,Robocon 2024,Robocon 24
Classifier: Programming Language :: Python :: 3
Classifier: License :: OSI Approved :: MIT License
Classifier: Operating System :: OS Independent
License-File: LICENSE
Requires-Dist: opencv-python
Requires-Dist: ultralytics
